streamlit_option_menu/__init__.py
streamlit_option_menu/streamlit_callback.py
streamlit_option_menu/frontend/dist/index.html
streamlit_option_menu/frontend/dist/css/app.1b9a5a45.css
streamlit_option_menu/frontend/dist/css/chunk-vendors.9a0195bf.css
streamlit_option_menu/frontend/dist/fonts/bootstrap-icons.ba49e844.woff
streamlit_option_menu/frontend/dist/fonts/bootstrap-icons.cc1e5eda.woff2
streamlit_option_menu/frontend/dist/js/app.df603dc4.js
streamlit_option_menu/frontend/dist/js/app.df603dc4.js.map
streamlit_option_menu/frontend/dist/js/chunk-vendors.a8e82192.js
streamlit_option_menu/frontend/dist/js/chunk-vendors.a8e82192.js.map
streamlit_option_menu_patch-0.3.12.dist-info/LICENSE
streamlit_option_menu_patch-0.3.12.dist-info/METADATA
streamlit_option_menu_patch-0.3.12.dist-info/WHEEL
streamlit_option_menu_patch-0.3.12.dist-info/top_level.txt
streamlit_option_menu_patch-0.3.12.dist-info/RECORD
