Metadata-Version: 2.1
Name: streamlit-option-menu-patch
Version: 0.3.12
Summary: streamlit-option-menu is a simple Streamlit component that allows users to select a single item from a list of options in a menu.
Home-page: https://github.com/victoryhb/streamlit-option-menu
Author: Victor Yan
Author-email: victoryhb@163.com
Requires-Python: >=3.6
License-File: LICENSE
Requires-Dist: streamlit >=0.63
